nomad_analysis/__init__.py
nomad_analysis/analysis_source.py
nomad_analysis/utils.py
nomad_analysis/actions/__init__.py
nomad_analysis/actions/schema.py
nomad_analysis/general/__init__.py
nomad_analysis/general/schema.py
nomad_analysis/jupyter/__init__.py
nomad_analysis/jupyter/schema.py
nomad_analysis-0.2.1.dist-info/licenses/LICENSE
nomad_analysis-0.2.1.dist-info/METADATA
nomad_analysis-0.2.1.dist-info/WHEEL
nomad_analysis-0.2.1.dist-info/entry_points.txt
nomad_analysis-0.2.1.dist-info/top_level.txt
nomad_analysis-0.2.1.dist-info/RECORD
