Metadata-Version: 2.4
Name: nomad-analysis
Version: 0.2.1
Summary: A NOMAD plugin for analysis of FAIR data.
Author-email: Sarthak Kapoor <sarthak.kapoor@physik.hu-berlin.de>, "Jose M. Pizarro" <jose.pizarro@physik.hu-berlin.de>, Andrea Albino <andrea.albino@physik.hu-berlin.de>, Hampus Näsström <hampus.naesstroem@physik.hu-berlin.de>, Sebastian Brückner <sebastian.brueckner@ikz-berlin.de>
Maintainer-email: FAIRmat <fairmat@physik.hu-berlin.de>
License:                                  Apache License
Project-URL: Repository, https://github.com/FAIRmat-NFDI/nomad-analysis
Project-URL: Documentation, https://fairmat-nfdi.github.io/nomad-analysis/
Classifier: Intended Audience :: Developers
Classifier: Operating System :: OS Independent
Classifier: Programming Language :: Python
Classifier: Programming Language :: Python :: 3.10
Classifier: Programming Language :: Python :: 3.11
Classifier: Programming Language :: Python :: 3.12
Classifier: License :: OSI Approved :: Apache Software License
Requires-Python: >=3.10
License-File: LICENSE
Requires-Dist: nomad-lab>=1.3.14
Requires-Dist: nbformat>=5.9.2
Provides-Extra: dev
Requires-Dist: nomad-lab[infrastructure]>=1.3.14; extra == "dev"
Requires-Dist: ruff; extra == "dev"
Requires-Dist: pytest; extra == "dev"
Requires-Dist: structlog; extra == "dev"
Dynamic: license-file
